handwritting_generator_light/__init__.py
handwritting_generator_light/font.py
handwritting_generator_light/generator.py
handwritting_generator_light/test.py
handwritting_generator_light/content/Jayadhira.ttf
handwritting_generator_light/content/Lemon Tuesday.otf
handwritting_generator_light/content/amandasignature.ttf
handwritting_generator_light/content/back.png
handwritting_generator_light/content/bimbo.regular.ttf
handwritting_generator_light/content/form1.png
handwritting_generator_light/content/form2.png
handwritting_generator_light/content/form2_wide.png
handwritting_generator_light/content/form3.png
handwritting_generator_light/content/grid_wide.png
handwritting_generator_light/content/lines.png
handwritting_generator_light/content/lines_wide.png
handwritting_generator_light/content/mathilde.regular.otf
handwritting_generator_light/content/ofont.ru_BetinaScriptCTT.ttf
handwritting_generator_light/content/ofont.ru_Denistina.ttf
handwritting_generator_light/content/ofont.ru_Eskal.ttf
handwritting_generator_light/content/ofont.ru_Marutya.ttf
handwritting_generator_light/content/ofont.ru_Rozovii Chulok.ttf
handwritting_generator_light/content/ofont.ru_Shlapak Script.otf
handwritting_generator_light/content/passport.png
handwritting_generator_light/content/passport1.png
handwritting_generator_light/content/passport2.png
handwritting_generator_light/content/passport3.png
handwritting_generator_light/content/passport4.png
handwritting_generator_light/content/passport4_wide.png
handwritting_generator_light/content/passport5.png
handwritting_generator_light/content/passport5_wide.png
handwritting_generator_light/content/passport6.png
handwritting_generator_light/content/passport6_wide.png
handwritting_generator_light/content/passport7.png
handwritting_generator_light/content/passport7_wide_exp.png
handwritting_generator_light/content/passport_wide.png
handwritting_generator_light/content/scrumble1.png
handwritting_generator_light/content/scrumble1_wide.png
handwritting_generator_light-0.2.dist-info/METADATA
handwritting_generator_light-0.2.dist-info/WHEEL
handwritting_generator_light-0.2.dist-info/top_level.txt
handwritting_generator_light-0.2.dist-info/RECORD
